fuzzing_utils/__init__.py
fuzzing_utils/constants.py
fuzzing_utils/conversion.py
fuzzing_utils/core.py
fuzzing_utils/training.py
fuzzing_utils/data/iris.csv
fuzzing_utils-0.0.3.dist-info/LICENSE
fuzzing_utils-0.0.3.dist-info/METADATA
fuzzing_utils-0.0.3.dist-info/WHEEL
fuzzing_utils-0.0.3.dist-info/top_level.txt
fuzzing_utils-0.0.3.dist-info/RECORD
