Metadata-Version: 2.1
Name: fuzzing-utils
Version: 0.0.3
Summary: A set of utility functions for testing templates within mlighter
Home-page: https://github.com/dakaidan/FuzzingUtils
Author: Aidan Dakhama
Author-email: ai.dakhama@gmail.com
Classifier: Programming Language :: Python :: 3
Classifier: License :: OSI Approved :: Apache Software License
Classifier: Operating System :: OS Independent
Requires-Python: >=3.6
License-File: LICENSE
Requires-Dist: numpy
Requires-Dist: pandas
Requires-Dist: scikit-learn
Provides-Extra: test
Requires-Dist: pytest ; extra == 'test'
